hide/__init__.py
hide/cli.py
hide/crypt.py
hide/gui.py
privacy_guide-0.0.1.dist-info/METADATA
privacy_guide-0.0.1.dist-info/WHEEL
privacy_guide-0.0.1.dist-info/entry_points.txt
privacy_guide-0.0.1.dist-info/licenses/LICENSE.txt
privacy_guide-0.0.1.dist-info/RECORD
